{
  "version": 1,
  "updated": "2026-07-17T18:48:11Z",
  "tags": [
    {
      "name": "STPAT",
      "author": "SaintPat",
      "file": "stpat-e2bb5bd3.r2tag.zip",
      "uploaded": "2026-07-17T18:47:52Z",
      "startgg": {
        "slug": "user/e2bb5bd3",
        "tag": "SaintPat"
      }
    },
    {
      "name": "jakey",
      "author": "Emerald_87",
      "file": "jakey-83e6fb3e.r2tag.zip",
      "uploaded": "2026-07-17T01:13:43Z",
      "startgg": {
        "slug": "user/83e6fb3e",
        "tag": "Emerald_87"
      }
    },
    {
      "name": "ALVRG",
      "author": "JuanSolo",
      "file": "alvrg-ea2886ed.r2tag.zip",
      "uploaded": "2026-07-16T21:54:22Z",
      "startgg": {
        "slug": "user/ea2886ed",
        "tag": "JuanSolo"
      }
    },
    {
      "name": "WIZ",
      "author": "",
      "file": "wiz-1c171446.r2tag.zip",
      "uploaded": "2026-07-14T22:05:35Z",
      "startgg": {
        "slug": "user/1c171446",
        "tag": "Shadowwiz"
      }
    },
    {
      "name": "DALEK",
      "author": "Ada",
      "file": "dalek-1aa1dcdd.r2tag.zip",
      "uploaded": "2026-07-10T21:44:36Z",
      "startgg": {
        "slug": "user/1aa1dcdd",
        "tag": "Dalek Ditto"
      }
    },
    {
      "name": "BOX",
      "author": "Spyker",
      "file": "box-000adab7.r2tag.zip",
      "uploaded": "2026-07-09T20:09:25Z",
      "startgg": {
        "slug": "user/000adab7",
        "tag": "Spyker"
      }
    },
    {
      "name": "JUGZ!",
      "author": "",
      "file": "jugz-6192f6f1.r2tag.zip",
      "uploaded": "2026-07-08T06:32:43Z",
      "startgg": {
        "slug": "user/6192f6f1",
        "tag": "jugeeya"
      }
    },
    {
      "name": "KIM",
      "author": "kimchi",
      "file": "kim-e85def91.r2tag.zip",
      "uploaded": "2026-07-02T17:02:14Z",
      "startgg": {
        "slug": "user/e85def91",
        "tag": "Kimchi"
      }
    },
    {
      "name": "HYPER",
      "author": "HyperFlame",
      "file": "hyper-8ada046a.r2tag.zip",
      "uploaded": "2026-06-22T02:35:12Z",
      "startgg": {
        "slug": "user/8ada046a",
        "tag": "HyperFlame"
      }
    },
    {
      "name": "ANI",
      "author": "",
      "file": "ani-a48d0512.r2tag.zip",
      "uploaded": "2026-06-19T07:56:02Z",
      "startgg": {
        "slug": "user/a48d0512",
        "tag": "Ani"
      }
    },
    {
      "name": "BRUJITA",
      "author": "",
      "file": "brujita-8f5808e7.r2tag.zip",
      "uploaded": "2026-06-18T19:51:09Z",
      "startgg": {
        "slug": "user/8f5808e7",
        "tag": "Brujita"
      }
    }
  ]
}
